nanopq/__init__.py
nanopq/convert_faiss.py
nanopq/opq.py
nanopq/pq.py
nanopq-0.2.2.dist-info/licenses/LICENSE
nanopq-0.2.2.dist-info/METADATA
nanopq-0.2.2.dist-info/WHEEL
nanopq-0.2.2.dist-info/top_level.txt
nanopq-0.2.2.dist-info/RECORD
