Metadata-Version: 2.4
Name: nanopq
Version: 0.2.2
Summary: Pure python implementation of product quantization for nearest neighbor search 
Home-page: https://github.com/matsui528/nanopq
Author: Yusuke Matsui
Author-email: matsui528@gmail.com
License: MIT
License-File: LICENSE
Requires-Dist: numpy
Requires-Dist: scipy
Provides-Extra: dev
Requires-Dist: mypy; extra == "dev"
Dynamic: author
Dynamic: author-email
Dynamic: description
Dynamic: description-content-type
Dynamic: home-page
Dynamic: license
Dynamic: license-file
Dynamic: provides-extra
Dynamic: requires-dist
Dynamic: summary
